openapi_client/__init__.py
openapi_client/api_client.py
openapi_client/configuration.py
openapi_client/exceptions.py
openapi_client/model_utils.py
openapi_client/rest.py
openapi_client/swx_api_client.py
openapi_client/api/__init__.py
openapi_client/api/actions_api.py
openapi_client/api/collections_api.py
openapi_client/api/events_api.py
openapi_client/api/items_api.py
openapi_client/api/model_versions_api.py
openapi_client/api/models_api.py
openapi_client/api/properties_api.py
openapi_client/api/things_api.py
openapi_client/apis/__init__.py
openapi_client/model/__init__.py
openapi_client/model/action_delay.py
openapi_client/model/action_delay_input.py
openapi_client/model/action_delay_input_properties.py
openapi_client/model/action_delay_input_properties_input.py
openapi_client/model/action_delay_list_response.py
openapi_client/model/action_delay_response.py
openapi_client/model/action_delete_response.py
openapi_client/model/action_list_response.py
openapi_client/model/action_reboot.py
openapi_client/model/action_reboot_response.py
openapi_client/model/action_request.py
openapi_client/model/action_request_delay.py
openapi_client/model/action_request_delay_input.py
openapi_client/model/action_response_element1.py
openapi_client/model/action_response_element1_delay.py
openapi_client/model/action_response_element2.py
openapi_client/model/action_response_element2_delay.py
openapi_client/model/action_response_element2_delay_input.py
openapi_client/model/action_response_element3.py
openapi_client/model/action_response_element3_reboot.py
openapi_client/model/action_update_request.py
openapi_client/model/action_update_request_delay.py
openapi_client/model/action_update_response.py
openapi_client/model/action_update_response_delay.py
openapi_client/model/collection_list_response.py
openapi_client/model/collection_list_response_paging.py
openapi_client/model/collection_request.py
openapi_client/model/collection_response.py
openapi_client/model/collection_update_request.py
Altair_Smartworks_SDK-0.0.1.dist-info/METADATA
Altair_Smartworks_SDK-0.0.1.dist-info/WHEEL
Altair_Smartworks_SDK-0.0.1.dist-info/top_level.txt
Altair_Smartworks_SDK-0.0.1.dist-info/RECORD
