Metadata-Version: 2.1
Name: Altair-Smartworks-SDK
Version: 0.0.1
Summary: Digital Model API (WIP)
Home-page: UNKNOWN
Author: Smartworks SDK TF
Author-email: 
License: UNKNOWN
Keywords: OpenAPI,OpenAPI-Generator,Digital Model API (WIP)
Platform: UNKNOWN
Requires-Python: >=3.6
Requires-Dist: urllib3 (>=1.25.3)
Requires-Dist: python-dateutil
